__init__.py
envplay.py
ldnsexplorer/DNS_APP.py
ldnsexplorer/__init__.py
ldnsexplorer/__main__.py
ldnsexplorer/find_local_resolver.py
ldnsexplorer/measure_dns.py
ldnsexplorer/measure_tcp.py
ldnsexplorer/tcp_client.py
ldns_explorer-1.3.dist-info/METADATA
ldns_explorer-1.3.dist-info/WHEEL
ldns_explorer-1.3.dist-info/top_level.txt
ldns_explorer-1.3.dist-info/RECORD
