Metadata-Version: 2.1
Name: ldns-explorer
Version: 1.3
Summary: A public DNS resolver explorer
Author: cwru
Classifier: Programming Language :: Python
Classifier: Operating System :: OS Independent
Requires-Python: >=3
Requires-Dist: matplotlib
Requires-Dist: dnspython
